builder_io/__init__.py
builder_io/api.py
builder_io/builder_types.py
builder_io/middlewares.py
builder_io/py.typed
builder_io/utils.py
builder_io-0.2.0.dist-info/METADATA
builder_io-0.2.0.dist-info/WHEEL
builder_io-0.2.0.dist-info/licenses/LICENSE
builder_io-0.2.0.dist-info/RECORD
