Metadata-Version: 2.4
Name: builder-io
Version: 0.2.0
Summary: Builder.io Unofficial Python SDK.
Project-URL: homepage, https://github.com/MicaelJarniac/builder-io
Project-URL: source, https://github.com/MicaelJarniac/builder-io
Project-URL: download, https://pypi.org/project/builder-io/#files
Project-URL: changelog, https://github.com/MicaelJarniac/builder-io/blob/main/docs/CHANGELOG.md
Project-URL: documentation, https://builder-io.readthedocs.io
Project-URL: issues, https://github.com/MicaelJarniac/builder-io/issues
Author-email: Micael Jarniac <micael@jarniac.dev>
License: MIT
License-File: LICENSE
Classifier: Development Status :: 1 - Planning
Classifier: License :: OSI Approved :: MIT License
Classifier: Natural Language :: English
Classifier: Operating System :: OS Independent
Classifier: Programming Language :: Python :: 3
Classifier: Typing :: Typed
Requires-Python: >=3.13
Requires-Dist: aiohttp>=3.12.15
Requires-Dist: loguru>=0.7.3
Requires-Dist: pydantic>=2.11.7
Requires-Dist: yarl>=1.20.1
